{
  "symbol": "AAPL",
  "regime_metrics": {
    "BULLISH": {
      "total_return": 0.010261405012599756,
      "sharpe": 9.742185912248173,
      "max_drawdown": -0.000821008715554295,
      "win_rate": null,
      "avg_trade_return": null,
      "num_trades": 0,
      "avg_position_size": -0.185545297713984,
      "kelly_stats": {
        "count": 6,
        "mean": -0.185545297713984,
        "median": -0.15329519314805656,
        "std": 0.2311276080192983,
        "p10": -0.4529990841171436,
        "p90": 0.04965838412324802
      }
    },
    "SIDEWAYS": {
      "total_return": 0.10766946229706442,
      "sharpe": 4.983855598303819,
      "max_drawdown": -0.004141274492317202,
      "win_rate": 0.6666666666666666,
      "avg_trade_return": 0.009130727480116844,
      "num_trades": 15,
      "avg_position_size": 0.009760855680594642,
      "kelly_stats": {
        "count": 54,
        "mean": 0.009760855680594642,
        "median": -0.07887041772395686,
        "std": 0.32911394474783046,
        "p10": -0.29143886809816894,
        "p90": 0.5388653388924763
      }
    },
    "BEARISH": null
  },
  "transitions": [
    {
      "index": 54,
      "from": "SIDEWAYS",
      "to": "BULLISH",
      "before_return": -0.00019618712858060494,
      "after_return": 0.010933739703318235,
      "detection_lag_days": 0
    }
  ],
  "transition_summary": {
    "SIDEWAYS->BULLISH": {
      "count": 1,
      "avg_before_return": -0.00019618712858060494,
      "avg_after_return": 0.010933739703318235,
      "avg_detection_lag_days": 0.0
    }
  }
}